__init__.py
georef_ar_py/__init__.py
georef_ar_py/__main__.py
georef_ar_py/commands.py
georef_ar_py/constants.py
georef_ar_py/context.py
georef_ar_py/diff.py
georef_ar_py/exceptions.py
georef_ar_py/georequests.py
georef_ar_py/info.py
georef_ar_py/normalization.py
georef_ar_py/similar.py
georef_ar_py/territorial.py
georef_ar_py/utils.py
georef_ar_py-0.0.6.dist-info/LICENSE
georef_ar_py-0.0.6.dist-info/METADATA
georef_ar_py-0.0.6.dist-info/WHEEL
georef_ar_py-0.0.6.dist-info/entry_points.txt
georef_ar_py-0.0.6.dist-info/top_level.txt
georef_ar_py-0.0.6.dist-info/RECORD
