Metadata-Version: 2.1
Name: georef-ar-py
Version: 0.0.6
Summary: Paquete para consultas y procesamiento de respuestas sobre la API de georef-ar
Author-email: "Pablo E. Andino" <pabloe.andino@gmail.com>
Project-URL: Homepage, https://github.com/pavloae/georef-ar-py
Project-URL: Bug Tracker, https://github.com/pavloae/georef-ar-py/issues
Classifier: Programming Language :: Python :: 3
Classifier: License :: OSI Approved :: MIT License
Classifier: Operating System :: OS Independent
Requires-Python: >=3.7
License-File: LICENSE
Requires-Dist: requests ~=2.29.0
Requires-Dist: deepdiff ~=6.3.0
Requires-Dist: pandas ==2.0.2
Requires-Dist: aiohttp ~=3.8.3
Requires-Dist: numpy ~=1.24.4
Provides-Extra: cli
Requires-Dist: click ==8.1.3 ; extra == 'cli'
Requires-Dist: tqdm ==4.65.0 ; extra == 'cli'
